<annotation>
	<folder>train</folder>
	<filename>Scrapper_158.jpg</filename>
	<path>/home/snm/Desktop/images/train/Scrapper_158.jpg</path>
	<source>
		<database>Unknown</database>
	</source>
	<size>
		<width>187</width>
		<height>250</height>
		<depth>3</depth>
	</size>
	<segmented>0</segmented>
	<object>
		<name>blackbengal</name>
		<pose>Unspecified</pose>
		<truncated>0</truncated>
		<difficult>0</difficult>
		<bndbox>
			<xmin>45</xmin>
			<ymin>76</ymin>
			<xmax>145</xmax>
			<ymax>135</ymax>
		</bndbox>
	</object>
</annotation>
